hblock/__init__.py
hblock/appindicator_replacement.py
hblock/data/__init__.py
hblock/data/hblock-disabled.png
hblock/data/hblock-enabled.png
hblock/data/hblock.png
hblock-0.0.6.dist-info/DESCRIPTION.rst
hblock-0.0.6.dist-info/METADATA
hblock-0.0.6.dist-info/RECORD
hblock-0.0.6.dist-info/WHEEL
hblock-0.0.6.dist-info/entry_points.txt
hblock-0.0.6.dist-info/metadata.json
hblock-0.0.6.dist-info/top_level.txt
