Metadata-Version: 2.0
Name: hblock
Version: 0.0.6
Summary: Hostname adblocker in your System Tray
Home-page: http://githup.com/artiya4u/hblock
Author: Artiya Thinkumpang
Author-email: artiya4u@gmail.com
License: MIT
Keywords: adblocker tray system tray icon
Platform: UNKNOWN
Requires-Dist: requests (>=2.2.1)
